README.md
pyproject.toml
setup.py
solar_mapper/__init__.py
solar_mapper/eval.py
solar_mapper/train.py
solar_mapper.egg-info/PKG-INFO
solar_mapper.egg-info/SOURCES.txt
solar_mapper.egg-info/dependency_links.txt
solar_mapper.egg-info/requires.txt
solar_mapper.egg-info/top_level.txt
solar_mapper/datamodules/__init__.py
solar_mapper/datamodules/mnist_datamodule.py
solar_mapper/datamodules/components/__init__.py
solar_mapper/models/__init__.py
solar_mapper/models/mnist_module.py
solar_mapper/models/components/__init__.py
solar_mapper/models/components/simple_dense_net.py
solar_mapper/tasks/__init__.py
solar_mapper/tasks/eval_task.py
solar_mapper/tasks/train_task.py
solar_mapper/utils/__init__.py
solar_mapper/utils/pylogger.py
solar_mapper/utils/rich_utils.py
solar_mapper/utils/utils.py
tests/__init__.py
tests/conftest.py
tests/test_configs.py
tests/test_eval.py
tests/test_mnist_datamodule.py
tests/test_sweeps.py
tests/test_train.py
tests/helpers/__init__.py
tests/helpers/package_available.py
tests/helpers/run_if.py
tests/helpers/run_sh_command.py