Metadata-Version: 2.1
Name: solar-mapper
Version: 0.0.1
Summary: Global Solar Mapping with Satellite Imagery
Home-page: https://github.com/jacobbieker/solar-mapper
Author: Jacob Bieker
Author-email: jacob@bieker.tech
